aio_insight/__init__.py
aio_insight/aio_api_client.py
aio_insight/aio_insight.py
aio_insight/aio_query_insight.py
tests/__init__.py
tests/test_aio_insight.py
aio_insight-1.0.5.dist-info/LICENSE
aio_insight-1.0.5.dist-info/METADATA
aio_insight-1.0.5.dist-info/WHEEL
aio_insight-1.0.5.dist-info/top_level.txt
aio_insight-1.0.5.dist-info/RECORD
