Metadata-Version: 2.1
Name: aio-insight
Version: 1.0.5
Summary: A Python library for asynchronous querying of Jira Insight API.
Home-page: https://github.com/g-rd/aio_insight
Author: Gerd Kukemilk
Author-email: 
License: Apache License 2.0
Project-URL: Homepage, https://github.com/g-rd/aio_insight
Classifier: Programming Language :: Python :: 3
Classifier: License :: OSI Approved :: Apache Software License
Classifier: Operating System :: OS Independent
Requires-Python: >=3.7
License-File: LICENSE
Requires-Dist: aiofiles==24.1.0
Requires-Dist: anyio==4.4.0
Requires-Dist: certifi==2024.7.4
Requires-Dist: h11==0.14.0
Requires-Dist: httpcore==1.0.5
Requires-Dist: httpx==0.27.0
Requires-Dist: idna==3.7
Requires-Dist: oauthlib==3.2.2
Requires-Dist: six==1.16.0
Requires-Dist: sniffio==1.3.1
